techmo_client/Dockerfile
techmo_client/README.md
techmo_client/VERSION.py
techmo_client/__init__.py
techmo_client/build_docker_image.sh
techmo_client/dictation_client.py
techmo_client/docker/run_dictation_client_python.sh
techmo_client/docker/tls/.gitkeep
techmo_client/docker/wav/.gitkeep
techmo_client/make_proto.sh
techmo_client/requirements.txt
techmo_client/run.sh
techmo_client/service/__init__.py
techmo_client/service/dictation_asr_pb2.py
techmo_client/service/dictation_asr_pb2_grpc.py
techmo_client/service/dictation_settings.py
techmo_client/service/streaming_recognizer.py
techmo_client/setup.sh
techmo_client/utils/__init__.py
techmo_client/utils/audio_source.py
techmo_client/utils/mic_source.py
techmo_client-0.1.0.dist-info/WHEEL
techmo_client-0.1.0.dist-info/METADATA
techmo_client-0.1.0.dist-info/RECORD
