Metadata-Version: 2.1
Name: techmo-client
Version: 0.1.0
Summary: 
Author: Marek Radecki
Author-email: marek.radecki@gmail.com
Requires-Python: >=3.8,<4.0
Classifier: Programming Language :: Python :: 3
Classifier: Programming Language :: Python :: 3.8
Classifier: Programming Language :: Python :: 3.9
Requires-Dist: PyAudio (==0.2.11)
Requires-Dist: gapic-google-cloud-speech-v1 (==0.15.3)
Requires-Dist: google-api-core (==1.27.0)
Requires-Dist: google-auth (==1.21.1)
Requires-Dist: google-auth-httplib2 (==0.0.3)
Requires-Dist: google-cloud-core (==1.0.2)
Requires-Dist: google-cloud-speech (==1.0.0)
Requires-Dist: googleapis-common-protos (==1.6.0)
Requires-Dist: grpc-google-cloud-speech-v1 (==0.8.1)
Requires-Dist: grpcio (==1.38.1)
Requires-Dist: grpcio-tools (==1.38.1)
Requires-Dist: httplib2 (==0.14.0)
Requires-Dist: oauth2client (==2.0.0)
Requires-Dist: proto-google-cloud-speech-v1 (==0.15.3)
Requires-Dist: protobuf (==3.12.2)
Requires-Dist: pydub (==0.23.1)
Requires-Dist: setuptools (==50.3.2)
